mopidy_webm3u/__init__.py
mopidy_webm3u/backend.py
mopidy_webm3u/ext.conf
mopidy_webm3u/m3u.py
mopidy_webm3u/types.py
Mopidy_WebM3U-0.1.3.dist-info/LICENSE
Mopidy_WebM3U-0.1.3.dist-info/METADATA
Mopidy_WebM3U-0.1.3.dist-info/WHEEL
Mopidy_WebM3U-0.1.3.dist-info/entry_points.txt
Mopidy_WebM3U-0.1.3.dist-info/top_level.txt
Mopidy_WebM3U-0.1.3.dist-info/RECORD
