Metadata-Version: 2.1
Name: Mopidy-WebM3U
Version: 0.1.3
Summary: Mopidy plugin to play M3U playlists that are hosted on a web server
Home-page: https://github.com/mgoltzsche/mopidy-webm3u
Author: Max Goltzsche
Author-email: max.goltzsche@gmail.com
License: Apache License, Version 2.0
Platform: UNKNOWN
Classifier: Environment :: No Input/Output (Daemon)
Classifier: Intended Audience :: End Users/Desktop
Classifier: License :: OSI Approved :: Apache Software License
Classifier: Operating System :: OS Independent
Classifier: Programming Language :: Python :: 2
Classifier: Topic :: Multimedia :: Sound/Audio :: Players
License-File: LICENSE
Requires-Dist: setuptools
Requires-Dist: Mopidy >=3.4.2
Requires-Dist: Pykka >=4.0.2
